{"isSuccess":true,"url":"http://rosettacode.org//wiki/Averages/Arithmetic_mean","codeArray":["function mean(array) {\n    var sum = 0,\n        i;\n    for (i = 0; i < array.length; i++) {\n        sum += array[i];\n    }\n    return array.length ? sum / array.length : 0;\n}\nalert(mean([1, 2, 3, 4, 5])); // 3\nalert(mean([])); // 0","function mean(array) {\n    var sum = 0;\n    array.forEach(function(value) {\n        sum += value;\n    });\n    return array.length ? sum / array.length : 0;\n}\nalert(mean([1, 2, 3, 4, 5])); // 3","function mean(array) {\n    return !array.length ? 0 :\n        array.reduce(function(pre, cur, i) {\n            return (pre * i + cur) / (i + 1);\n        });\n}\nalert(mean([1, 2, 3, 4, 5])); // 3\nalert(mean([])); // 0","Array.prototype.mean = function() {\n    return !this.length ? 0 :\n        this.reduce(function(pre, cur, i) {\n            return (pre * i + cur) / (i + 1);\n        });\n}\nalert([1, 2, 3, 4, 5].mean()); // 3\nalert([].mean()); // 0","function mean(a) {\n    return a.length ? Functional.reduce('+', 0, a) / a.length : 0;\n}"],"uncertainCodeArray":[],"textArray":[]}