{"isSuccess":true,"url":"http://rosettacode.org//wiki/Death_Star","codeArray":[" <!DOCTYPE html>\n  <html>\n  <body style=\"margin:0\">\n    <canvas id=\"myCanvas\" width=\"250\" height=\"250\" style=\"border:1px solid #d3d3d3;\">\n      Your browser does not support the HTML5 canvas tag.\n    </canvas>\n    <script>\n      var c = document.getElementById(\"myCanvas\");\n      var ctx = c.getContext(\"2d\");\n      //Fill the canvas with a dark gray background\n      ctx.fillStyle = \"#222222\";\n      ctx.fillRect(0,0,250,250);\n      // Create radial gradient for large base circle\n      var grd = ctx.createRadialGradient(225,175,190,225,150,130);\n      grd.addColorStop(0,\"#EEEEEE\");\n      grd.addColorStop(1,\"black\");\n      //Apply gradient and fill circle\n      ctx.fillStyle = grd;\n      ctx.beginPath();\n      ctx.arc(125,125,105,0,2*Math.PI);\n      ctx.fill();\n      // Create linear gradient for small inner circle\n      var grd = ctx.createLinearGradient(75,90,102,90);\n      grd.addColorStop(0,\"black\");\n      grd.addColorStop(1,\"gray\");\n      //Apply gradient and fill circle\n      ctx.fillStyle = grd;\n      ctx.beginPath();\n      ctx.arc(90,90,30,0,2*Math.PI);\n      ctx.fill();\n      //Add another small circle on top of the previous one to enhance the \"shadow\"\n      ctx.fillStyle = \"black\";\n      ctx.beginPath();\n      ctx.arc(80,90,17,0,2*Math.PI);\n      ctx.fill();\n    </script> \n  </body>\n  </html>"],"uncertainCodeArray":[],"textArray":[]}