{"isSuccess":true,"url":"http://rosettacode.org//wiki/Fractran","codeArray":[" var num = new Array();\n var den = new Array();\n var val;\n\n function compile(prog) {\n     var regex = /\\s*(\\d*)\\s*\\/\\s*(\\d*)\\s*(.*)/m;\n     while (regex.test(prog)) {\n         num.push(regex.exec(prog)[1]);\n         den.push(regex.exec(prog)[2]);\n         prog = regex.exec(prog)[3];\n     }\n }\n\n function dump(prog) {\n     for (var i = 0; i < num.length; i++)\n         document.body.innerHTML += num[i] + \"/\" + den[i] + \" \";\n     document.body.innerHTML += \"<br>\";\n }\n\n function step(val) {\n     var i = 0;\n     while (i < den.length && val % den[i] != 0) i++;\n     return num[i] * val / den[i];\n }\n\n function exec(val) {\n     var i = 0;\n     while (val && i < limit) {\n         document.body.innerHTML += i + \": \" + val + \"<br>\";\n         val = step(val);\n         i++;\n     }\n }\n // Main\n compile(\"17/91 78/85 19/51 23/38 29/33 77/29 95/23 77/19 1/17 11/13 13/11 15/14 15/2 55/1\");\n dump();\n var limit = 15;\n exec(2);"],"uncertainCodeArray":[],"textArray":[]}