{"isSuccess":true,"url":"http://rosettacode.org//wiki/S-Expressions","codeArray":["String.prototype.parseSexpr = function() {\n  \tvar t = this.match(/\\s*(\"[^\"]*\"|\\(|\\)|\"|[^\\s()\"]+)/g)\n  \tfor (var o, c=0, i=t.length-1; i>=0; i--) {\n  \t\tvar n, ti = t[i].trim()\n  \t\tif (ti == '\"') return\n  \t\telse if (ti == '(') t[i]='[', c+=1\n  \t\telse if (ti == ')') t[i]=']', c-=1\n  \t\telse if ((n=+ti) == ti) t[i]=n\n  \t\telse t[i] = '\\'' + ti.replace('\\'', '\\\\\\'') + '\\''\n  \t\tif (i>0 && ti!=']' && t[i-1].trim()!='(' ) t.splice(i,0, ',')\n  \t\tif (!c) if (!o) o=true; else return\n  \t}\n  \treturn c ? undefined : eval(t.join(''))\n  }\n  Array.prototype.toString = function() {\n  \tvar s=''; for (var i=0, e=this.length; i<e; i++) s+=(s?' ':'')+this[i]\n  \treturn '('+s+')'\n  }\n  Array.prototype.toPretty = function(s) {\n  \tif (!s) s = ''\n  \tvar r = s + '(<br>'\n  \tvar s2 = s + Array(6).join('&nbsp;')\n  \tfor (var i=0, e=this.length; i<e; i+=1) { \n  \t\tvar ai = this[i]\n  \t\tr += ai.constructor != Array ? s2+ai+'<br>' : ai.toPretty(s2)\n  \t}\n  \treturn r + s + ')<br>'\n  }\n  var str = '((data \"quoted data\" 123 4.5)\\n (data (!@# (4.5) \"(more\" \"data)\")))'\n  document.write('text:<br>', str.replace(/\\n/g,'<br>').replace(/ /g,'&nbsp;'), '<br><br>')\n  var sexpr = str.parseSexpr()\n  if (sexpr === undefined) \n  \tdocument.write('Invalid s-expr!', '<br>')\n  else \n  \tdocument.write('s-expr:<br>', sexpr, '<br><br>', sexpr.constructor != Array ? '' : 'pretty print:<br>' + sexpr.toPretty())"],"uncertainCodeArray":[],"textArray":[]}