{"isSuccess":true,"url":"http://rosettacode.org//wiki/SEDOLs","codeArray":["function sedol(input) {\n    return input + sedol_check_digit(input);\n}\nvar weight = [1, 3, 1, 7, 3, 9, 1];\n\nfunction sedol_check_digit(char6) {\n    if (char6.search(/^[0-9BCDFGHJKLMNPQRSTVWXYZ]{6}$/) == -1)\n        throw \"Invalid SEDOL number '\" + char6 + \"'\";\n    var sum = 0;\n    for (var i = 0; i < char6.length; i++)\n        sum += weight[i] * parseInt(char6.charAt(i), 36);\n    var check = (10 - sum % 10) % 10;\n    return check.toString();\n}\nvar input = [\n    '710889', 'B0YBKJ', '406566', 'B0YBLH', '228276',\n    'B0YBKL', '557910', 'B0YBKR', '585284', 'B0YBKT',\n    \"BOATER\", \"12345\", \"123456\", \"1234567\"\n];\nvar expected = [\n    '7108899', 'B0YBKJ7', '4065663', 'B0YBLH2', '2282765',\n    'B0YBKL9', '5579107', 'B0YBKR5', '5852842', 'B0YBKT7',\n    null, null, '1234563', null\n];\nfor (var i in input) {\n    try {\n        var sedolized = sedol(input[i]);\n        if (sedolized == expected[i])\n            print(sedolized);\n        else\n            print(\"error: calculated sedol for input \" + input[i] +\n                \" is \" + sedolized + \", but it should be \" + expected[i]\n            );\n    } catch (e) {\n        print(\"error: \" + e);\n    }\n}"],"uncertainCodeArray":[],"textArray":[]}